aioskynet/__init__.py
aioskynet/client.py
aioskynet/constants.py
aioskynet/errors.py
aioskynet/file.py
aioskynet-1.0.0.dist-info/LICENSE
aioskynet-1.0.0.dist-info/WHEEL
aioskynet-1.0.0.dist-info/METADATA
aioskynet-1.0.0.dist-info/RECORD
